pstree/__init__.py
pstree/cluster_gp_sklearn.py
pstree/cluster_gp_tools.py
pstree/common_utils.py
pstree/complexity_utils.py
pstree/custom_sklearn_tools.py
pstree/gp_function.py
pstree/gp_visualization_utils.py
pstree/multigene_gp.py
pstree-0.1.2.dist-info/AUTHORS.rst
pstree-0.1.2.dist-info/LICENSE
pstree-0.1.2.dist-info/METADATA
pstree-0.1.2.dist-info/WHEEL
pstree-0.1.2.dist-info/top_level.txt
pstree-0.1.2.dist-info/RECORD
