Metadata-Version: 2.1
Name: pstree
Version: 0.1.2
Summary: An open source python library for non-linear piecewise symbolic regression based on Genetic Programming
Home-page: https://github.com/hengzhe-zhang/pstree
Author: Hengzhe Zhang
Author-email: zhenlingcn@foxmail.com
License: MIT license
Keywords: pstree
Classifier: Development Status :: 2 - Pre-Alpha
Classifier: Intended Audience :: Developers
Classifier: License :: OSI Approved :: MIT License
Classifier: Natural Language :: English
Classifier: Programming Language :: Python :: 3
Classifier: Programming Language :: Python :: 3.6
Classifier: Programming Language :: Python :: 3.7
Classifier: Programming Language :: Python :: 3.8
Requires-Python: >=3.6
License-File: LICENSE
License-File: AUTHORS.rst
Requires-Dist: numpy
Requires-Dist: pandas
Requires-Dist: gplearn
Requires-Dist: scipy
Requires-Dist: deap
Requires-Dist: bluepyopt
Requires-Dist: glmnet
Requires-Dist: icecream
Requires-Dist: scikit-learn
